CHANGES.txt
LICENSE.txt
MANIFEST.in
README.txt
setup.py
js/__init__.py
js.jquery_numeric.egg-info/PKG-INFO
js.jquery_numeric.egg-info/SOURCES.txt
js.jquery_numeric.egg-info/dependency_links.txt
js.jquery_numeric.egg-info/entry_points.txt
js.jquery_numeric.egg-info/namespace_packages.txt
js.jquery_numeric.egg-info/not-zip-safe
js.jquery_numeric.egg-info/requires.txt
js.jquery_numeric.egg-info/top_level.txt
js/jquery_numeric/__init__.py
js/jquery_numeric/test_jquery_numeric.txt
js/jquery_numeric/resources/jquery.numeric.js
js/jquery_numeric/resources/jquery.numeric.min.js