Metadata-Version: 1.0
Name: js.jquery-numeric
Version: 1.4.1
Summary: Fanstatic packaging of jquery numeric
Home-page: UNKNOWN
Author: Fanstatic Developers
Author-email: fanstatic@googlegroups.com
License: BSD
Platform: UNKNOWN
